iotools/__init__.py
iotools/_default_decode_encode.py
iotools/_generic_open.py
iotools/_help_utils.py
iotools/_missing_module_helper.py
iotools/_temp_filename_utils.py
iotools/aviio.py
iotools/bytesio.py
iotools/csvio.py
iotools/examples/examples_avi.py
iotools/examples/examples_avi_using_cv2.py
iotools/examples/examples_avi_using_imageio.py
iotools/examples/examples_bytes.py
iotools/examples/examples_csv.py
iotools/examples/examples_csv_using_csv.py
iotools/examples/examples_csv_using_pandas.py
iotools/examples/examples_gif.py
iotools/examples/examples_gif_using_imageio.py
iotools/examples/examples_gz.py
iotools/examples/examples_image.py
iotools/examples/examples_image_using_cv2.py
iotools/examples/examples_image_using_imageio.py
iotools/examples/examples_image_using_pil.py
iotools/examples/examples_image_using_skimage.py
iotools/examples/examples_jpg.py
iotools/examples/examples_jpg_using_cv2.py
iotools/examples/examples_jpg_using_imageio.py
iotools/examples/examples_jpg_using_pil.py
iotools/examples/examples_jpg_using_skimage.py
iotools/examples/examples_json.py
iotools/examples/examples_mp4.py
iotools/examples/examples_mp4_using_cv2.py
iotools/examples/examples_mp4_using_imageio.py
iotools/examples/examples_npy.py
iotools/examples/examples_pickle.py
iotools/examples/examples_png.py
iotools/examples/examples_png_using_cv2.py
iotools/examples/examples_png_using_imageio.py
iotools/examples/examples_png_using_pil.py
iotools/examples/examples_png_using_skimage.py
iotools/examples/examples_tar.py
iotools/examples/examples_txt.py
iotools/examples/examples_video.py
iotools/examples/examples_video_using_cv2.py
iotools/examples/examples_video_using_imageio.py
iotools/examples/examples_xml.py
iotools/examples/examples_yaml.py
iotools/examples/examples_zip.py
iotools/examples/examples_zst.py
iotools/gifio.py
iotools/gzio.py
iotools/imageio.py
iotools/jpgio.py
iotools/jsonio.py
iotools/localfs.py
iotools/mp4io.py
iotools/npyio.py
iotools/pickleio.py
iotools/pngio.py
iotools_wrappers-0.1.1.dist-info/LICENSE.txt
iotools_wrappers-0.1.1.dist-info/METADATA
iotools_wrappers-0.1.1.dist-info/WHEEL
iotools_wrappers-0.1.1.dist-info/RECORD
