Metadata-Version: 2.1
Name: iotools-wrappers
Version: 0.1.1
Summary: Provides a unified syntax for reading and writing data to files
Home-page: https://github.com/albanpierre/iotools-wrappers
License: MIT
Author: Alban Pierre
Author-email: apierre.work@pm.me
Requires-Python: >=3.10,<4
Classifier: License :: OSI Approved :: MIT License
Classifier: Programming Language :: Python :: 3
Classifier: Programming Language :: Python :: 3.10
Classifier: Programming Language :: Python :: 3.11
Requires-Dist: fsspec (>=2022.11.0,<2023.0.0)
Project-URL: Repository, https://github.com/albanpierre/iotools-wrappers
